envoy/annotations/deprecation_pb2.py
envoy/annotations/deprecation_pb2.pyi
envoy/annotations/resource_pb2.py
envoy/annotations/resource_pb2.pyi
envoy/config/accesslog/v3/accesslog_pb2.py
envoy/config/accesslog/v3/accesslog_pb2.pyi
envoy/config/bootstrap/v3/bootstrap_pb2.py
envoy/config/bootstrap/v3/bootstrap_pb2.pyi
envoy/config/cluster/v3/circuit_breaker_pb2.py
envoy/config/cluster/v3/circuit_breaker_pb2.pyi
envoy/config/cluster/v3/cluster_pb2.py
envoy/config/cluster/v3/cluster_pb2.pyi
envoy/config/cluster/v3/filter_pb2.py
envoy/config/cluster/v3/filter_pb2.pyi
envoy/config/cluster/v3/outlier_detection_pb2.py
envoy/config/cluster/v3/outlier_detection_pb2.pyi
envoy/config/core/v3/address_pb2.py
envoy/config/core/v3/address_pb2.pyi
envoy/config/core/v3/backoff_pb2.py
envoy/config/core/v3/backoff_pb2.pyi
envoy/config/core/v3/base_pb2.py
envoy/config/core/v3/base_pb2.pyi
envoy/config/core/v3/config_source_pb2.py
envoy/config/core/v3/config_source_pb2.pyi
envoy/config/core/v3/event_service_config_pb2.py
envoy/config/core/v3/event_service_config_pb2.pyi
envoy/config/core/v3/extension_pb2.py
envoy/config/core/v3/extension_pb2.pyi
envoy/config/core/v3/grpc_method_list_pb2.py
envoy/config/core/v3/grpc_method_list_pb2.pyi
envoy/config/core/v3/grpc_service_pb2.py
envoy/config/core/v3/grpc_service_pb2.pyi
envoy/config/core/v3/health_check_pb2.py
envoy/config/core/v3/health_check_pb2.pyi
envoy/config/core/v3/http_uri_pb2.py
envoy/config/core/v3/http_uri_pb2.pyi
envoy/config/core/v3/protocol_pb2.py
envoy/config/core/v3/protocol_pb2.pyi
envoy/config/core/v3/proxy_protocol_pb2.py
envoy/config/core/v3/proxy_protocol_pb2.pyi
envoy/config/core/v3/resolver_pb2.py
envoy/config/core/v3/resolver_pb2.pyi
envoy/config/core/v3/socket_option_pb2.py
envoy/config/core/v3/socket_option_pb2.pyi
envoy/config/core/v3/substitution_format_string_pb2.py
envoy/config/core/v3/substitution_format_string_pb2.pyi
envoy/config/core/v3/udp_socket_config_pb2.py
envoy/config/core/v3/udp_socket_config_pb2.pyi
reboot-0.44.0.dist-info/licenses/LICENSE
reboot-0.44.0.dist-info/METADATA
reboot-0.44.0.dist-info/WHEEL
reboot-0.44.0.dist-info/entry_points.txt
reboot-0.44.0.dist-info/top_level.txt
reboot-0.44.0.dist-info/RECORD
