Metadata-Version: 2.4
Name: reboot
Version: 0.44.0
Summary: The Reboot library
License-Expression: Apache-2.0
Classifier: Operating System :: MacOS :: MacOS X
Classifier: Programming Language :: Python :: 3
Requires-Python: <3.13,>=3.10
License-File: LICENSE
Requires-Dist: aiofiles==23.2.1
Requires-Dist: aiohttp==3.13.2
Requires-Dist: colorama==0.4.6
Requires-Dist: cryptography==44.0.0
Requires-Dist: cffi==1.17.1
Requires-Dist: googleapis-common-protos==1.65.0
Requires-Dist: grpc-interceptor==0.15.4
Requires-Dist: grpcio==1.64.3
Requires-Dist: grpcio-health-checking==1.64.3
Requires-Dist: grpcio-reflection==1.64.3
Requires-Dist: grpcio-status==1.64.3
Requires-Dist: grpcio-tools==1.64.3
Requires-Dist: h2==4.3.0
Requires-Dist: jinja2==3.1.2
Requires-Dist: jinja2-strcase==0.0.2
Requires-Dist: kubernetes-asyncio==31.1.0
Requires-Dist: mypy-protobuf==3.6.0
Requires-Dist: packaging>=23.1
Requires-Dist: pathspec==0.12.1
Requires-Dist: protobuf==5.28.3
Requires-Dist: psutil==6.0.0
Requires-Dist: pyjwt==2.10.1
Requires-Dist: pyprctl==0.1.3
Requires-Dist: pyyaml==6.0.2
Requires-Dist: sortedcontainers==2.4.0
Requires-Dist: typing-extensions>=4.9.0
Requires-Dist: tzlocal==5.3
Requires-Dist: urllib3==1.26.15
Requires-Dist: watchdog==6.0.0
Requires-Dist: websockets==15.0.1
Requires-Dist: uuid7-standard>=1.1.0
Requires-Dist: tabulate==0.9.0
Requires-Dist: opentelemetry-api==1.28.1
Requires-Dist: opentelemetry-sdk==1.28.1
Requires-Dist: opentelemetry-exporter-otlp-proto-grpc==1.28.1
Requires-Dist: opentelemetry-instrumentation-grpc==0.49b1
Requires-Dist: fastapi==0.115.12
Requires-Dist: uvicorn==0.34.0
Requires-Dist: pydantic>=2.7.4
Requires-Dist: bitarray==3.8.0
Dynamic: license-file
